groupdocs_annotation_cloud/__init__.py
groupdocs_annotation_cloud/api_client.py
groupdocs_annotation_cloud/api_exception.py
groupdocs_annotation_cloud/auth.py
groupdocs_annotation_cloud/configuration.py
groupdocs_annotation_cloud/rest.py
groupdocs_annotation_cloud/apis/__init__.py
groupdocs_annotation_cloud/apis/annotate_api.py
groupdocs_annotation_cloud/apis/file_api.py
groupdocs_annotation_cloud/apis/folder_api.py
groupdocs_annotation_cloud/apis/info_api.py
groupdocs_annotation_cloud/apis/license_api.py
groupdocs_annotation_cloud/apis/preview_api.py
groupdocs_annotation_cloud/apis/storage_api.py
groupdocs_annotation_cloud/models/__init__.py
groupdocs_annotation_cloud/models/annotate_options.py
groupdocs_annotation_cloud/models/annotation_api_link.py
groupdocs_annotation_cloud/models/annotation_info.py
groupdocs_annotation_cloud/models/annotation_reply_info.py
groupdocs_annotation_cloud/models/api_error.py
groupdocs_annotation_cloud/models/api_error_response.py
groupdocs_annotation_cloud/models/consumption_result.py
groupdocs_annotation_cloud/models/disc_usage.py
groupdocs_annotation_cloud/models/document_info.py
groupdocs_annotation_cloud/models/error.py
groupdocs_annotation_cloud/models/error_details.py
groupdocs_annotation_cloud/models/file_info.py
groupdocs_annotation_cloud/models/file_version.py
groupdocs_annotation_cloud/models/file_versions.py
groupdocs_annotation_cloud/models/files_list.py
groupdocs_annotation_cloud/models/files_upload_result.py
groupdocs_annotation_cloud/models/format.py
groupdocs_annotation_cloud/models/formats_result.py
groupdocs_annotation_cloud/models/link.py
groupdocs_annotation_cloud/models/link_element.py
groupdocs_annotation_cloud/models/object_exist.py
groupdocs_annotation_cloud/models/page_image.py
groupdocs_annotation_cloud/models/page_images.py
groupdocs_annotation_cloud/models/page_info.py
groupdocs_annotation_cloud/models/point.py
groupdocs_annotation_cloud/models/preview_options.py
groupdocs_annotation_cloud-25.7.dist-info/licenses/LICENSE
groupdocs_annotation_cloud-25.7.dist-info/METADATA
groupdocs_annotation_cloud-25.7.dist-info/WHEEL
groupdocs_annotation_cloud-25.7.dist-info/top_level.txt
groupdocs_annotation_cloud-25.7.dist-info/RECORD
